scanet/__init__.py
scanet/coexpression.py
scanet/conv.py
scanet/download_db.py
scanet/drug_interactions.py
scanet/grn.py
scanet/infer_grn.py
scanet/plotting.py
scanet/plottingNetworks.py
scanet/preprocessing.py
scanet/pseudobulk.py
scanet/script.R
scanet/databases/__init__.py
scanet/databases/allTFs_hg38.txt
scanet/databases/allTFs_mm.txt
scanet/databases/motifs-v9-nr.hgnc-m0.001-o0.0.tbl
scanet/databases/motifs-v9-nr.mgi-m0.001-o0.0.tbl
scanet-0.1.11.dist-info/LICENSE
scanet-0.1.11.dist-info/METADATA
scanet-0.1.11.dist-info/WHEEL
scanet-0.1.11.dist-info/top_level.txt
scanet-0.1.11.dist-info/RECORD
