Metadata-Version: 2.1
Name: scanet
Version: 0.1.11
Summary: The python package for the scanet platform.
Home-page: https://github.com/oubounyt/SCANet
Author: Mhaned Oubounyt
Classifier: Programming Language :: Python :: 3
Classifier: License :: OSI Approved :: MIT License
Classifier: Operating System :: OS Independent
Requires-Python: >=3.6
License-File: LICENSE
Requires-Dist: scanpy >=1.9.1
Requires-Dist: pyscenic >=0.11.2
Requires-Dist: setuptools >=42
Requires-Dist: wheel
